jk_prettyprintobj/DumperSettings.py
jk_prettyprintobj/NamedTupleDumpMixinMeta.py
jk_prettyprintobj/RawValue.py
jk_prettyprintobj/_Bits.py
jk_prettyprintobj/_ByteChunker.py
jk_prettyprintobj/_ConverterFunctions.py
jk_prettyprintobj/_Hex.py
jk_prettyprintobj/__init__.py
jk_prettyprintobj/dumper.py
jk_prettyprintobj-0.2025.8.14.dist-info/licenses/LICENSE.txt
jk_prettyprintobj-0.2025.8.14.dist-info/WHEEL
jk_prettyprintobj-0.2025.8.14.dist-info/METADATA
jk_prettyprintobj-0.2025.8.14.dist-info/RECORD
