Metadata-Version: 2.4
Name: jk_prettyprintobj
Version: 0.2025.8.14
Summary: This python module provides a mixin for creating pretty debugging output for objects. This is especially useful for semi-complex data structures.
Keywords: pretty-print,debugging,debug
Author-email: Jürgen Knauth <pubsrc@binary-overflow.de>
Maintainer-email: Jürgen Knauth <pubsrc@binary-overflow.de>
Requires-Python: >=3.8
Classifier: Development Status :: 5 - Production/Stable
Classifier: License :: OSI Approved :: Apache Software License
Classifier: Programming Language :: Python :: 3
Classifier: Topic :: Software Development :: Testing
License-File: LICENSE.txt
